<?xml version="1.0"?>
<inventory xmlns="http://inventory0007.core.rapidesuite.com">
    <name>Manage Key Performance Indicators - Single threshold level value</name>
    <name_hash>RES_MANAGE_KEY_PERFORMANCE_IND</name_hash>
    <svn>
        <revision xmlns="http://xsdutility.configurator.erapidsuite.com">$Revision: $:</revision>
        <author xmlns="http://xsdutility.configurator.erapidsuite.com">$Author: $:</author>
        <date xmlns="http://xsdutility.configurator.erapidsuite.com">$Date: $:</date>
        <headURL xmlns="http://xsdutility.configurator.erapidsuite.com">$HeadURL: $:</headURL>
        <id xmlns="http://xsdutility.configurator.erapidsuite.com">$Id: $:</id>
    </svn>
    <type>HTMLFORM</type>
    <description/>
    <sequence>5</sequence>
    <parent_name>Manage Key Performance Indicators - Key Performance Indicator</parent_name>
    <function_ids>1002676</function_ids>
    <define_navigation_mapper>Manage Key Performance Indicators</define_navigation_mapper>
    <update_navigation_mapper>Manage Key Performance Indicators</update_navigation_mapper>
    <reversible>true</reversible>
    <field>
        <name>KPI Name</name>
        <name_hash>RES_KPI_NAME</name_hash>
        <parent_name>KPI Name</parent_name>
        <mandatory>true</mandatory>
        <substitution/>
        <max_size>-1</max_size>
        <component_of_primary_key>true</component_of_primary_key>
        <html_form_field_data>
            <rsc_column_type>KB</rsc_column_type>
            <html_template>INPUT</html_template>
            <html_tag_name>INPUT</html_tag_name>
            <html_id_attribute/>
            <html_name_attribute/>
            <html_title_attribute/>
            <map_table_name/>
            <map_column_name/>
            <html_text_node_value/>
        </html_form_field_data>
    </field>
    <field>
        <name>Threshold</name>
        <name_hash>RES_THRESHOLD</name_hash>
        <parent_name/>
        <mandatory>true</mandatory>
        <substitution/>
        <max_size>-1</max_size>
        <component_of_primary_key>false</component_of_primary_key>
        <html_form_field_data>
            <rsc_column_type>KB</rsc_column_type>
            <html_template>INPUT</html_template>
            <html_tag_name>INPUT</html_tag_name>
            <html_id_attribute/>
            <html_name_attribute/>
            <html_title_attribute/>
            <map_table_name/>
            <map_column_name/>
            <html_text_node_value/>
        </html_form_field_data>
    </field>
    <field>
        <name>KPI Value Compared to Threshold</name>
        <name_hash>RES_KPI_VALUE_COMPARED_TO_THRE</name_hash>
        <parent_name/>
        <mandatory>true</mandatory>
        <substitution/>
        <max_size>-1</max_size>
        <component_of_primary_key>true</component_of_primary_key>
        <html_form_field_data>
            <rsc_column_type>KB</rsc_column_type>
            <html_template>INPUT</html_template>
            <html_tag_name>INPUT</html_tag_name>
            <html_id_attribute/>
            <html_name_attribute/>
            <html_title_attribute/>
            <map_table_name/>
            <map_column_name/>
            <html_text_node_value/>
        </html_form_field_data>
    </field>
    <field>
        <name>Status Indicator</name>
        <name_hash>RES_STATUS_INDICATOR</name_hash>
        <parent_name/>
        <mandatory>true</mandatory>
        <substitution>Critical=Critical###At risk=At risk###On track=On track</substitution>
        <max_size>-1</max_size>
        <component_of_primary_key>false</component_of_primary_key>
        <html_form_field_data>
            <rsc_column_type>KB</rsc_column_type>
            <html_template>SELECT</html_template>
            <html_tag_name>SELECT</html_tag_name>
            <html_id_attribute/>
            <html_name_attribute/>
            <html_title_attribute/>
            <map_table_name/>
            <map_column_name/>
            <html_text_node_value/>
        </html_form_field_data>
    </field>
</inventory>
