<?xml version="1.0" encoding="UTF-8"?>
<data name="Manage Inventory Organizations - Lot Serial Number and Packing Unit" xmlns="http://data0000.configurator.erapidsuite.com">
<m>
<e>Manage Inventory Organizations</e>
</m>
<h>
<c>Organization</c>
<c>Classification</c>
<c>Lot Control - Uniqueness</c>
<c>Lot Control - Generation</c>
<c>Allow Different Lot Status</c>
<c>Automatically Create Lot UOM Conversion</c>
<c>Lot Generation - Prefix</c>
<c>Lot Generation - Total Length</c>
<c>Lot Generation - Zero pad suffix</c>
<c>Child Lot Control - Generation</c>
<c>Child Lot Control - Prefix</c>
<c>Child Lot Control - Total Length</c>
<c>Child Lot Control - Zero pad suffix</c>
<c>Copy lot attributes</c>
<c>Format validation</c>
<c>Serial Number Generation - Uniqueness</c>
<c>Serial Number Generation - Generation</c>
<c>Serial Number Generation - Prefix</c>
<c>Starting Serial Number</c>
<c>System Selects Serial Numbers</c>
<c>Packing Unit Generation - Total Length</c>
<c>Packing Unit Generation - Prefix</c>
<c>GS1-128</c>
<c>Starting Packing Unit</c>
<c>Suffix</c>
<c>RSC Data Label</c>
<c>Navigation Filter</c>
</h>
</data>
