<?xml version="1.0" encoding="UTF-8"?>
<data name="Manage Pricing Lookups - Standard Lookups" xmlns="http://data0000.configurator.erapidsuite.com">
<m>
<e>Manage Pricing Lookups</e>
</m>
<h>
<c>Lookup Type</c>
<c>Meaning</c>
<c>Description</c>
<c>Module</c>
<c>Customization Level</c>
<c>REST Access Secured</c>
<c>RSC Data Label</c>
<c>Navigation Filter</c>
</h>
<r>
<c>ORA_QP_CUST_PRICING_SEGMENTS</c>
<c>Pricing Segments</c>
<c>List of pricing segments.</c>
<c>Pricing Administration</c>
<c>Extension</c>
<c/>
<c>DEFAULT.4</c>
<c>Manage Pricing Lookups</c>
</r>
</data>
